mariadb_dyncol/__init__.py
mariadb_dyncol/base.py
mariadb_dyncol/py.typed
mariadb_dyncol-3.6.1.dist-info/LICENSE
mariadb_dyncol-3.6.1.dist-info/METADATA
mariadb_dyncol-3.6.1.dist-info/WHEEL
mariadb_dyncol-3.6.1.dist-info/top_level.txt
mariadb_dyncol-3.6.1.dist-info/RECORD
