Metadata-Version: 2.1
Name: mariadb-dyncol
Version: 3.6.1
Summary: Pack/unpack Python dicts into/out of MariaDB's Dynamic Columns format.
Home-page: https://github.com/adamchainz/mariadb-dyncol
Author: Adam Johnson
Author-email: me@adamj.eu
License: MIT
Project-URL: Changelog, https://github.com/adamchainz/mariadb-dyncol/blob/main/HISTORY.rst
Project-URL: Twitter, https://twitter.com/adamchainz
Keywords: MariaDB
Classifier: Development Status :: 7 - Inactive
Classifier: Intended Audience :: Developers
Classifier: License :: OSI Approved :: MIT License
Classifier: Natural Language :: English
Classifier: Operating System :: OS Independent
Classifier: Programming Language :: Python :: 3 :: Only
Classifier: Programming Language :: Python :: 3
Classifier: Programming Language :: Python :: 3.7
Classifier: Programming Language :: Python :: 3.8
Classifier: Programming Language :: Python :: 3.9
Classifier: Programming Language :: Python :: 3.10
Classifier: Programming Language :: Python :: 3.11
Classifier: Typing :: Typed
Requires-Python: >=3.7
License-File: LICENSE
